senzing_core/__init__.py
senzing_core/_helpers.py
senzing_core/py.typed
senzing_core/szabstractfactory.py
senzing_core/szconfig.py
senzing_core/szconfigmanager.py
senzing_core/szdiagnostic.py
senzing_core/szengine.py
senzing_core/szproduct.py
senzing_core-1.0.3.dist-info/licenses/LICENSE
senzing_core-1.0.3.dist-info/METADATA
senzing_core-1.0.3.dist-info/WHEEL
senzing_core-1.0.3.dist-info/top_level.txt
senzing_core-1.0.3.dist-info/RECORD
