Metadata-Version: 2.4
Name: senzing_core
Version: 1.0.3
Summary: Senzing Python SDK
Home-page: https://github.com/senzing-garage/sz-sdk-python-core
Author: senzing
Author-email: support@senzing.com
License: Apache 2
Project-URL: Bug Tracker, https://github.com/senzing-garage/sz-sdk-python-core/issues
Classifier: Programming Language :: Python :: 3
Classifier: License :: OSI Approved :: Apache Software License
Classifier: Operating System :: OS Independent
Requires-Python: >=3.9
License-File: LICENSE
Requires-Dist: senzing>=4.0.0
Dynamic: license-file
